[
    {
        "name": "Alioth",
        "color": "#d5e0ff",
        "mass": 7.230122e+30,
        "radius": 2513638.25
    },
    {
        "name": "Kidishi",
        "color": "#3654c5",
        "parent": "Alioth",
        "mass": 8.9196938e+24,
        "radius": 7349.001,
        "e": 0.00669295,
        "a": 1.481707e+9,
        "i": 6.2799963,
        "raan": 2.9670597,
        "arg": 2.9941647,
        "v": 5.1953041
    },
    {
        "name": "1",
        "color": "#e0c1a0",
        "parent": "Kidishi",
        "mass": 4.5327480e+20,
        "radius": 302.235,
        "e": 0.00129015243,
        "a": 58482.5556,
        "i": 6.2831800,
        "raan": 1.25,
        "arg": 4.95,
        "v": 1.634349356891
    },
    {
        "name": "2",
        "color": "#6b5350",
        "parent": "Kidishi",
        "mass": 4.4909440e+20,
        "radius": 284.124,
        "e": 0.00157121991,
        "a": 82210.1518,
        "i": 0.0000018,
        "raan": 0.99,
        "arg": 3.19,
        "v": 0.5990875958338
    },
    {
        "name": "3",
        "color": "#888a93",
        "parent": "Kidishi",
        "mass": 6.9275200e+20,
        "radius": 345.58,
        "e": 0.00223588832,
        "a": 102884.0585,
        "i": 6.2654977,
        "raan": 1.85,
        "arg": 3.86,
        "v": 2.31529250718
    },
    {
        "name": "4",
        "color": "#6a6b78",
        "parent": "Kidishi",
        "mass": 9.3521520e+22,
        "radius": 1403.7,
        "e": 0.0406238458,
        "a": 282184.024,
        "i": 0.0164141,
        "raan": 5.51,
        "arg": 4.52,
        "v": 2.33
    },
    {
        "name": "5",
        "color": "#e6e7f0",
        "parent": "Kidishi",
        "mass": 1.9707600e+22,
        "radius": 1409.5,
        "e": 0.00645174439,
        "a": 688458.319,
        "i": 0.0078586,
        "raan": 3.35,
        "arg": 2.66,
        "v": 0.37
    },
    {
        "name": "6",
        "color": "#6080c8",
        "parent": "Kidishi",
        "mass": 2.4186600e+23,
        "radius": 2291.8,
        "e": 0.01669295,
        "a": 3573848.8714,
        "i": 2.6950770,
        "raan": 4.34,
        "arg": 6.09,
        "v": 0.55
    }
]